biobb_structure_manager/__init__.py
biobb_structure_manager/data_lib_manager.py
biobb_structure_manager/mmb_server.py
biobb_structure_manager/model_utils.py
biobb_structure_manager/modeller_manager.py
biobb_structure_manager/mutation_manager.py
biobb_structure_manager/residue_lib_manager.py
biobb_structure_manager/sequence_manager.py
biobb_structure_manager/structure_manager.py
biobb_structure_manager-3.0.2.dist-info/METADATA
biobb_structure_manager-3.0.2.dist-info/WHEEL
biobb_structure_manager-3.0.2.dist-info/top_level.txt
biobb_structure_manager-3.0.2.dist-info/RECORD
