Metadata-Version: 2.1
Name: biobb-structure-manager
Version: 3.0.2
Summary: BioBB_structure_manager is a library to efficiently load and process biomolecular 3D structures.
Home-page: https://github.com/bioexcel/biobb_structure_manager
Author: Biobb developers
Author-email: josep.gelpi@bsc.es
License: UNKNOWN
Project-URL: Documentation, http://biobb_structure_manager.readthedocs.io/en/latest/
Project-URL: Bioexcel, https://bioexcel.eu/
Keywords: Bioinformatics Workflows BioExcel Compatibility
Platform: UNKNOWN
Classifier: Development Status :: 3 - Alpha
Classifier: Programming Language :: Python :: 3.7
Classifier: License :: OSI Approved :: Apache Software License
Classifier: Operating System :: MacOS :: MacOS X
Classifier: Operating System :: POSIX
Requires-Python: ==3.7.*
Requires-Dist: biopython (==1.76)
